[
  {"id":"person1",
   "label":"Deval Agrifarman",
   "shape":"circularImage",
   "image":"https://pbs.twimg.com/profile_images/3147240448/937d6098f8d6d2ca2c4d4b965f40d633_400x400.jpeg",
   "group":"main"
  },
  {"id":"biography1",
   "label":"Biography",
   "shape":"icon",
   "icon": {
     "face":"Ionicons",
     "code":"\uf3a0"
   },  
   "group":"main"
  },
  {"id":"biography1a",
   "label":"Male",
   "shape":"icon",
   "icon": {
     "face":"FontAwesome",
     "code":"\uf183"
   },  
   "group":"sub"
  },
  {"id":"biography1b",
   "label":"Surabaya",
   "shape":"icon",
   "icon": {
     "face":"Ionicons",
     "code":"\uf3a0"
   },  
   "group":"sub"
  },
  {"id":"biography1c",
   "label":"INTP",
   "shape":"icon",
   "icon": {
     "face":"Ionicons",
     "code":"\uf3a0"
   },  
   "group":"sub"
  }

  
  
]
